PrintTolTest/__init__.py
PrintTolTest/cli.py
PrintTolTest/tolerance.py
printtoltest-0.2.2.1.dist-info/licenses/LICENSE.md
printtoltest-0.2.2.1.dist-info/METADATA
printtoltest-0.2.2.1.dist-info/WHEEL
printtoltest-0.2.2.1.dist-info/entry_points.txt
printtoltest-0.2.2.1.dist-info/top_level.txt
printtoltest-0.2.2.1.dist-info/RECORD
