Metadata-Version: 2.4
Name: PrintTolTest
Version: 0.2.2.1
Summary: A simple CLI tool to calculate 3D print dimensional tolerance.
Author: NanashiTheNameless
Author-email: NanashiTheNameless <NanashiTheNameless@NamelessNanashi.dev>
Maintainer: NanashiTheNameless
Maintainer-email: NanashiTheNameless <NanashiTheNameless@NamelessNanashi.dev>
License: OQL-1.2
Project-URL: Download, https://github.com/NanashiTheNameless/PrintTolTest/releases/latest
Project-URL: Homepage, https://github.com/NanashiTheNameless/PrintTolTest
Project-URL: GitHub-Sponsor, https://github.com/sponsors/NanashiTheNameless
Project-URL: BuyMeACoffee, https://buymeacoffee.com/NamelessNanashi
Classifier: Development Status :: 4 - Beta
Classifier: Natural Language :: English
Classifier: Programming Language :: Python
Classifier: Programming Language :: Python :: 3
Classifier: Programming Language :: Python :: 3 :: Only
Classifier: Programming Language :: Python :: 3.10
Classifier: Programming Language :: Python :: 3.11
Classifier: Programming Language :: Python :: 3.12
Classifier: Programming Language :: Python :: 3.13
Classifier: Programming Language :: Python :: 3.14
Requires-Python: >=3.10
License-File: LICENSE.md
Dynamic: license-file
